[
  {
    "uuid": "4p9hbcmaFJnSCZvCrZ3oCL",
    "description": "Mode U CW Beacon",
    "alive": true,
    "type": "Transmitter",
    "uplink_low": null,
    "uplink_high": null,
    "uplink_drift": null,
    "downlink_low": 435352000,
    "downlink_high": null,
    "downlink_drift": null,
    "mode": "CW",
    "mode_id": 6,
    "uplink_mode": null,
    "invert": false,
    "baud": 0,
    "sat_id": "JQJE-9408-3483-0314-4576",
    "norad_cat_id": 27939,
    "norad_follow_id": null,
    "status": "active",
    "updated": "2019-04-18T05:39:53.343316Z",
    "citation": "CITATION NEEDED - https://xkcd.com/285/",
    "service": "Unknown",
    "iaru_coordination": "N/A",
    "iaru_coordination_url": "",
    "itu_notification": {
      "urls": []
    },
    "frequency_violation": false,
    "unconfirmed": false
  },
  {
    "uuid": "FyC3BE75BxrFU25Lk5XLCN",
    "description": "PE0SAT - CW Beacon",
    "alive": true,
    "type": "Transmitter",
    "uplink_low": null,
    "uplink_high": null,
    "uplink_drift": null,
    "downlink_low": 435352800,
    "downlink_high": null,
    "downlink_drift": null,
    "mode": "CW",
    "mode_id": 6,
    "uplink_mode": null,
    "invert": false,
    "baud": null,
    "sat_id": "JQJE-9408-3483-0314-4576",
    "norad_cat_id": 27939,
    "norad_follow_id": null,
    "status": "active",
    "updated": "2019-04-18T05:39:53.343316Z",
    "citation": "CITATION NEEDED - https://xkcd.com/285/",
    "service": "Unknown",
    "iaru_coordination": "N/A",
    "iaru_coordination_url": "",
    "itu_notification": {
      "urls": []
    },
    "frequency_violation": false,
    "unconfirmed": false
  },
  {
    "uuid": "eXpwEmjNcom9kzRsYNGcyF",
    "description": "Mode U FM Doka",
    "alive": true,
    "type": "Transmitter",
    "uplink_low": null,
    "uplink_high": null,
    "uplink_drift": null,
    "downlink_low": 435353000,
    "downlink_high": null,
    "downlink_drift": null,
    "mode": "DOKA",
    "mode_id": 96,
    "uplink_mode": null,
    "invert": false,
    "baud": 1200,
    "sat_id": "JQJE-9408-3483-0314-4576",
    "norad_cat_id": 27939,
    "norad_follow_id": null,
    "status": "active",
    "updated": "2022-08-01T16:56:50.716892Z",
    "citation": "https://network.satnogs.org/observations/3172080/",
    "service": "Amateur",
    "iaru_coordination": "N/A",
    "iaru_coordination_url": "",
    "itu_notification": {
      "urls": []
    },
    "frequency_violation": false,
    "unconfirmed": false
  }
]